gaffer/__init__.py
gaffer/errors.py
gaffer/operations.py
gaffer/store.py
pygaffer-0.1.dist-info/DESCRIPTION.rst
pygaffer-0.1.dist-info/METADATA
pygaffer-0.1.dist-info/RECORD
pygaffer-0.1.dist-info/WHEEL
pygaffer-0.1.dist-info/metadata.json
pygaffer-0.1.dist-info/top_level.txt
