Metadata-Version: 2.0
Name: pygaffer
Version: 0.1
Summary: Python Gaffer API
Home-page: https://github.com/cybermaggedon/pygaffer
Author: cybermaggedon
Author-email: cybermaggedon@gmail.com
License: UNKNOWN
Platform: UNKNOWN
Classifier: Programming Language :: Python :: 3
Classifier: Operating System :: OS Independent
Requires-Dist: requests
